{
  "version": "2.1",
  "timestamp": "2026-01-11T15:04:32.432Z",
  "inputMode": "discord",
  "electionName": "Senate Election January 2026 (Term 43)",
  "candidates": [
    "DinoCompactor",
    "IsraelGPT",
    "CreepilyCreep",
    "Dr Bacon Hair",
    "Ratat0ing",
    "Complexii",
    "CEO Zolo",
    "councilor _peemcgee",
    "toasttastesprettygood",
    "HsmNewfriend",
    "Josh ‚Äúalleged terrorist‚Äù Hillman"
  ],
  "ballots": [
    {
      "voter": "therecycler",
      "rankings": [
        "Ratat0ing",
        "Dr Bacon Hair",
        "HsmNewfriend",
        "hg_weighty",
        "JoshHillman",
        "minemaster",
        "DinoCompactor",
        "zolo17"
      ]
    },
    {
      "voter": "alzubloxxer11",
      "rankings": [
        "Dr Bacon Hair",
        "HsmNewfriend",
        "Mayor Ratat0ing",
        "CreepilyCreep",
        "Complexii",
        "Josh ‚Äúalleged terrorist‚Äù Hillman",
        "toasttastesprettygood"
      ]
    },
    {
      "voter": "stefanmakker",
      "rankings": [
        "HsmNewfriend",
        "Mayor Ratat0ing",
        "Dr Bacon Hair",
        "councilor _peemcgee",
        "Complexii",
        "toasttastesprettygood",
        "Josh ‚Äúalleged terrorist‚Äù Hillman"
      ]
    },
    {
      "voter": "lopsterbisque",
      "rankings": [
        "Mayor Ratat0ing",
        "CreepilyCreep",
        "Complexii",
        "CEO Zolo",
        "IsraelGPT",
        "councilor _peemcgee",
        "Dr Bacon Hair",
        "HsmNewfriend"
      ]
    },
    {
      "voter": "binchymonkey",
      "rankings": [
        "Hg_67",
        "IsraelGPT",
        "Mayor Ratat0ing",
        "Luci the Trident Farmer",
        "Josh ‚Äúalleged terrorist‚Äù Hillman"
      ]
    },
    {
      "voter": "drbaconhair",
      "rankings": [
        "toasttastesprettygood",
        "HsmNewfriend",
        "Dr Bacon Hair",
        "CEO Zolo",
        "Josh ‚Äúalleged terrorist‚Äù Hillman",
        "Mayor Ratat0ing",
        "CreepilyCreep",
        "IsraelGPT",
        "Luci the Trident Farmer",
        "councilor _peemcgee",
        "Complexii"
      ]
    },
    {
      "voter": "lucithetridentfarmer",
      "rankings": [
        "Luci the Trident Farmer",
        "Josh ‚Äúalleged terrorist‚Äù Hillman",
        "Dr Bacon Hair",
        "CreepilyCreep",
        "DinoCompactor",
        "councilor _peemcgee",
        "Complexii",
        "HsmNewfriend",
        "IsraelGPT"
      ]
    },
    {
      "voter": "ratat0ing",
      "rankings": [
        "Mayor Ratat0ing",
        "CreepilyCreep",
        "HsmNewfriend",
        "CEO Zolo",
        "Complexii",
        "Dr Bacon Hair",
        "toasttastesprettygood"
      ]
    },
    {
      "voter": "darkhelmet12e4",
      "rankings": [
        "Dr Bacon Hair",
        "CEO Zolo",
        "Lopster Bisque",
        "Anvil",
        "HsmNewfriend"
      ]
    },
    {
      "voter": "zolo",
      "rankings": [
        "Zolo",
        "Baconhair",
        "HsmNewfriend",
        "Complexii",
        "CreepilyCreep",
        "Ratatoing",
        "Toasttastesprettygood",
        "Markstefer"
      ]
    },
    {
      "voter": "cubine",
      "rankings": [
        "Dr Bacon Hair",
        "Anvil",
        "CreepilyCreep",
        "Luci the Trident Farmer"
      ]
    },
    {
      "voter": "hg_67",
      "rankings": [
        "MrJeremyFisher",
        "specificgjumguage",
        "Hg_67"
      ]
    },
    {
      "voter": "trial_len",
      "rankings": [
        "Dr Bacon Hair",
        "Mayor Ratat0ing",
        "toasttastesprettygood",
        "Lopster Bisque",
        "Anvil"
      ]
    },
    {
      "voter": "israelgpt",
      "rankings": [
        "IsraelGPT",
        "toasttastesprettygood",
        "Dr Bacon Hair",
        "Mayor Ratat0ing",
        "CreepilyCreep",
        "HsmNewfriend",
        "Josh ‚Äúalleged terrorist‚Äù Hillman",
        "Luci the Trident Farmer",
        "CEO Zolo",
        "councilor _peemcgee",
        "Complexii"
      ]
    },
    {
      "voter": "yodabird",
      "rankings": [
        "Complexii",
        "CreepilyCreep",
        "Ratat0ing",
        "zolo17",
        "HsmNewfriend",
        "JoshHillman",
        "DinoComparator",
        "Dr_Bacon_Hair",
        "_peemcgee",
        "Markstefer",
        "Lucinnefo",
        "minemaster933"
      ]
    },
    {
      "voter": "joshallegedterroristhillman",
      "rankings": [
        "JoshHillman",
        "Lucinnefo",
        "Dr Bacon Hair",
        "CreepilyCreep",
        "Ratatoing",
        "Complexiii",
        "Minemaster",
        "Peemcgee",
        "Dinocomparator",
        "HsmNewfriend",
        "Markstfu",
        "Zolo"
      ]
    },
    {
      "voter": "_peemcgee",
      "rankings": [
        "councilor _peemcgee",
        "Mayor Ratat0ing",
        "Josh ‚Äúalleged terrorist‚Äù Hillman",
        "CreepilyCreep",
        "Dr Bacon Hair"
      ]
    },
    {
      "voter": "jammymie",
      "rankings": [
        "Dr Bacon Hair",
        "CreepilyCreep",
        "HsmNewfriend",
        "CEO Zolo",
        "toasttastesprettygood"
      ]
    },
    {
      "voter": "sdorr",
      "rankings": [
        "toasttastesprettygood",
        "HsmNewfriend",
        "Dr Bacon Hair",
        "CEO Zolo"
      ]
    },
    {
      "voter": "mushroomcultist",
      "rankings": [
        "am",
        "Minemaster",
        "HsmNewfriend",
        "Drbaconhair",
        "Zolo"
      ]
    },
    {
      "voter": "dinocompactor",
      "rankings": [
        "am",
        "DinoComparator",
        "rat",
        "creep",
        "luci",
        "toast",
        "josh",
        "hsm",
        "complexii",
        ".zolo",
        "Bacon",
        "Isreal"
      ]
    },
    {
      "voter": "gold",
      "rankings": [
        "am",
        "Complexii",
        "CreepilyCreep",
        "Ratat0ing",
        "zolo17",
        "HsmNewfriend",
        "JoshHillman",
        "DinoComparator",
        "Dr_Bacon_Hair",
        "_peemcgee",
        "Markstefer",
        "minemaster933"
      ]
    },
    {
      "voter": "businessmindset101",
      "rankings": [
        "am",
        "Complexii",
        "zolo17",
        "JoshHillman",
        "HsmNewfriend",
        "Dr_Bacon_Hair",
        "Minemaster399",
        "creepilycreep",
        "Ratat0ing"
      ]
    },
    {
      "voter": "toasttastesprettygood",
      "rankings": [
        "am",
        "Minemaster",
        "HsmNewfriend",
        "Drbaconhair",
        "Zolo",
        "CreepilyCreep",
        "Ratatoing",
        "Markstefer"
      ]
    },
    {
      "voter": "gjum",
      "rankings": [
        "CreepilyCreep",
        "Ratat0ing",
        "Complexii",
        "HsmNewfriend",
        "Zolo",
        "DrBaconHair",
        "Minemaster",
        "peemcgee"
      ]
    },
    {
      "voter": "creepilycreep",
      "rankings": [
        "CreepilyCreep",
        "Ratat0ing",
        "Complexii",
        "DrBaconHair",
        "Zolo",
        "minemaster",
        "peemcgee",
        "JohnHillman"
      ]
    },
    {
      "voter": "complexii",
      "rankings": [
        "Complexii",
        "Mayor Ratat0ing",
        "CreepilyCreep",
        "CEO Zolo",
        "councilor _peemcgee",
        "HsmNewfriend",
        "Dr Bacon Hair"
      ]
    },
    {
      "voter": "juniortide",
      "rankings": [
        "Dr Bacon Hair",
        "CEO Zolo",
        "Creepily",
        "Complexii",
        "Joshhillman",
        "Ratat0ing",
        "Peemcgee",
        "Minemaster",
        "Hsmnewfriend",
        "Dino Comparator",
        "markstefer"
      ]
    },
    {
      "voter": "lordchieftain",
      "rankings": [
        "Mayor Ratat0ing",
        "CreepilyCreep",
        "Complexii",
        "HsmNewfriend",
        "CEO Zolo",
        "councilor _peemcgee",
        "Dr Bacon Hair",
        "Josh ‚Äúalleged terrorist‚Äù Hillman",
        "minemaster",
        "DinoCompactor",
        "IsraelGPT"
      ]
    },
    {
      "voter": "peterthusk",
      "rankings": [
        "Dr Baacon Hair",
        "Minemaster",
        "Rato0ing",
        "Zolo",
        "JoshHillman",
        "HsmNewfriend"
      ]
    },
    {
      "voter": "speedyjjustice",
      "rankings": [
        "Minemaster",
        "Hsmnewfriend",
        "DrBaconHair",
        "Markstefer",
        "Creepily Creep",
        "Ratatoing"
      ]
    },
    {
      "voter": "tukidokikiwi",
      "rankings": [
        "Minemaster",
        "Hsmnewfriend",
        "DrBaconHair",
        "Markstefer"
      ]
    },
    {
      "voter": "hsmnewfriend",
      "rankings": [
        "Minemaster",
        "HsmNewfriend",
        "DrBaconHair",
        "Markstefer",
        "Zolo17",
        "_peemcgee",
        "Lucinnefo",
        "JoshHillman",
        "Complexxi",
        "Creepilyceep",
        "Dinocomarator"
      ]
    },
    {
      "voter": "rattwinkii",
      "rankings": [
        "Complexii",
        "CreepilyCreep",
        "Ratat0ing",
        "zolo17",
        "HsmNewfriend",
        "JoshHillman",
        "DinoComparator",
        "Dr_Bacon_Hair",
        "_peemcgee",
        "Markstefer",
        "minemaster933"
      ]
    },
    {
      "voter": "saker",
      "rankings": [
        "Minemaster",
        "Hsmnewfriend",
        "DrBaconHair",
        "Markstefer",
        "Creepily Creep",
        "Ratatoing"
      ]
    },
    {
      "voter": "kronprinzkaiser",
      "rankings": [
        "Minemaster",
        "Hsmnewfriend",
        "DrBaconHair",
        "Markstefer",
        "Creepily Creep",
        "Ratatoing"
      ]
    },
    {
      "voter": "okiinawa",
      "rankings": [
        "Minemaster",
        "Hsmnewfriend",
        "DrBaconHair",
        "Markstefer",
        "Creepily Creep",
        "Ratatoing"
      ]
    },
    {
      "voter": "gilian",
      "rankings": [
        "toasttastesprettygood",
        "Drbaconhair",
        "Complexii",
        "hsmnewfriend",
        "Zolo18",
        "Wheatthinking",
        "Markstefer",
        "67 67 67"
      ]
    },
    {
      "voter": "escarchaking333",
      "rankings": [
        "Ratat0ing",
        "CreepilyCreep",
        "DrBaconHair",
        "Zolo",
        "minemaster",
        "peemcgee",
        "JohnHillman"
      ]
    },
    {
      "voter": "sage",
      "rankings": [
        ") creep",
        ") hsmnewfriend",
        ") peemcgee",
        ") drbaconhair",
        ") joshhillman",
        ") minemaster"
      ]
    },
    {
      "voter": "palantircios",
      "rankings": [
        "Mayor Ratat0ing",
        "CreepilyCreep",
        "Complexii",
        "Dr Bacon Hair",
        "HsmNewfriend",
        "IsraelGPT",
        "DinoCompactor",
        "CEO Zolo",
        "toasttastesprettygood"
      ]
    },
    {
      "voter": "ergeantclithorris666",
      "rankings": [
        "toasttastesprettygood",
        "Dr Bacon Hair",
        "HsmNewfriend",
        "CEO Zolo",
        "Complexii",
        "Hg_67",
        "Anvil",
        "august"
      ]
    },
    {
      "voter": "august",
      "rankings": [
        "toasttastesprettygood",
        "Mayor Ratat0ing",
        "Complexii",
        "CEO Zolo",
        "councilor _peemcgee",
        "CreepilyCreep",
        "HsmNewfriend",
        "IsraelGPT",
        "Dr Bacon Hair",
        "Josh ‚Äúalleged terrorist‚Äù Hillman",
        "DinoCompactor"
      ]
    },
    {
      "voter": "silent",
      "rankings": [
        "Dr Bacon Hair",
        "HsmNewfriend",
        "Mine master",
        "Mayor Ratat0ing",
        "councilor _peemcgee",
        "CEO Zolo",
        "DinoCompactor"
      ]
    },
    {
      "voter": "vedel",
      "rankings": [
        "Minemaster",
        "Hsmnewfriend",
        "DrBaconHair",
        "Markstefer",
        "Creepily Creep",
        "Ratatoing"
      ]
    }
  ],
  "rawDiscordInput": {
    "candidates": "@DinoCompactor \n@IsraelGPT \n@CreepilyCreep \n@Dr Bacon Hair(real) \n@Ratat0ing \n@Complexii \n@CEO Zolo \n@councilor _peemcgee \n@toasttastesprettygood \n@HsmNewfriend \n@Josh ‚Äúalleged terrorist‚Äù Hillman \n",
    "ballots": "Ex-Councilor TheRecycler\n\n ‚Äî 3/1/2026 6:12 am\nRatat0ing\nDr Bacon Hair\nHsmNewfriend\nhg_weighty\nJoshHillman\nminemaster\nDinoCompactor\nzolo17 \nAlzuBloxxer11 ‚Äî 3/1/2026 6:14 am\n@Dr Bacon Hair(real) \n@HsmNewfriend \n@Mayor Ratat0ing \n@CreepilyCreep \n@Complexii \n@Josh ‚Äúalleged terrorist‚Äù Hillman \n@toasttastesprettygood\nStefanMakker\n\n ‚Äî 3/1/2026 6:15 am\n@HsmNewfriend \n@Mayor Ratat0ing \n@Dr Bacon Hair(real) \n@councilor _peemcgee \n@Complexii \n@toasttastesprettygood \n@Josh ‚Äúalleged terrorist‚Äù Hillman \nLopster Bisque ‚Äî 3/1/2026 6:15 am\n@Mayor Ratat0ing \n@CreepilyCreep \n@Complexii \n@CEO Zolo \n@IsraelGPT \n@councilor _peemcgee \n@Dr Bacon Hair(real) \n@HsmNewfriend\nbinchymonkey\n\n ‚Äî 3/1/2026 6:16 am\n@Hg_67\n@IsraelGPT\n@Mayor Ratat0ing\n@Luci the Trident Farmer\n@Josh ‚Äúalleged terrorist‚Äù Hillman\n \nDr Bacon Hair(real)\n\n ‚Äî 3/1/2026 6:16 am\n@toasttastesprettygood \n@HsmNewfriend \n@Dr Bacon Hair(real) \n@CEO Zolo \n@Josh ‚Äúalleged terrorist‚Äù Hillman \n@Mayor Ratat0ing \n@CreepilyCreep \n@IsraelGPT \n@Luci the Trident Farmer \n@councilor _peemcgee \n@Complexii \nLuci the Trident Farmer\n\n ‚Äî 3/1/2026 6:19 am\n@Luci the Trident Farmer (wasnt i banned?)\n@Josh ‚Äúalleged terrorist‚Äù Hillman \n@Dr Bacon Hair(real) \n@CreepilyCreep \n@DinoCompactor \n@councilor _peemcgee \n@Complexii \n@HsmNewfriend \n@IsraelGPT\nMayor Ratat0ing\n\n ‚Äî 3/1/2026 6:20 am\n@Mayor Ratat0ing \n@CreepilyCreep \n@HsmNewfriend \n@CEO Zolo \n@Complexii \n@Dr Bacon Hair(real) \n@toasttastesprettygood \nDark Helmet12E4\n\n ‚Äî 3/1/2026 6:30 am\n@Dr Bacon Hair(real)\n @CEO Zolo \n@Lopster Bisque\n @Anvil\n@HsmNewfriend \nCEO Zolo\n\n ‚Äî 3/1/2026 6:32 am\nZolo\nBaconhair\nHsmNewfriend\nComplexii\nCreepilyCreep\nRatatoing\nToasttastesprettygood (minemaster)\nMarkstefer\nCubine\n\n ‚Äî 3/1/2026 6:33 am\n@Dr Bacon Hair(real) \n@Anvil \n@CreepilyCreep \n@Luci the Trident Farmer\nHg_67 ‚Äî 3/1/2026 6:36 am\n@MrJeremyFisher\n@specificgjumguage (write-in)\n@Hg_67 \ntrial_len (AKA Lena)\n\n ‚Äî 3/1/2026 7:03 am\n@Dr Bacon Hair(real) \n@Mayor Ratat0ing \n@toasttastesprettygood \n@Lopster Bisque \n@Anvil\nIsraelGPT ‚Äî 3/1/2026 7:16 am\n@IsraelGPT \n@toasttastesprettygood \n@Dr Bacon Hair(real) \n@Mayor Ratat0ing \n@CreepilyCreep \n@HsmNewfriend \n@Josh ‚Äúalleged terrorist‚Äù Hillman \n@Luci the Trident Farmer \n@CEO Zolo \n@councilor _peemcgee \n@Complexii\nturbo janny yodabird ‚Äî 3/1/2026 7:16 am\nComplexii\nCreepilyCreep\nRatat0ing\nzolo17\nHsmNewfriend\nJoshHillman\nDinoComparator\nDr_Bacon_Hair\n_peemcgee\nMarkstefer\nLucinnefo\nminemaster933\nJosh ‚Äúalleged terrorist‚Äù Hillman\n\n ‚Äî 3/1/2026 7:21 am\nJoshHillman\nLucinnefo (barred?)\nDr Bacon Hair\nCreepilyCreep\nRatatoing\nComplexiii\nMinemaster\nPeemcgee\nDinocomparator\nHsmNewfriend\nMarkstfu\n12.Zolo\nJuniorTide\n\n ‚Äî 3/1/2026 7:43 am\nLucinnefo was barred from senate.\nLuci the Trident Farmer\n\n ‚Äî 3/1/2026 7:50 am\ntgat what im saying\ncouncilor _peemcgee\n\n ‚Äî 3/1/2026 8:45 am\n@councilor _peemcgee \n@Mayor Ratat0ing \n@Josh ‚Äúalleged terrorist‚Äù Hillman \n@CreepilyCreep\n@Dr Bacon Hair(real)\njammy mie\n\n ‚Äî 3/1/2026 8:45 am\n@Dr Bacon Hair(real)\n@CreepilyCreep\n@HsmNewfriend \n@CEO Zolo\n@toasttastesprettygood \nSdorr\n\n ‚Äî 3/1/2026 9:09 am\n@toasttastesprettygood\n@HsmNewfriend\n3.@Dr Bacon Hair(real) \n@CEO Zolo\nmushroom cultist ‚Äî 3/1/2026 10:33 am\nMinemaster\nHsmNewfriend\nDrbaconhair\nZolo \nDinoCompactor ‚Äî 3/1/2026 10:48 am\n1.DinoComparator\n2.rat\n3.creep\n4.luci\n5.toast\n6.josh\n7.hsm\n8complexii\n9..zolo\n10.Bacon\n11.Isreal \nGold ‚Äî 3/1/2026 10:59 am\nComplexii\nCreepilyCreep\nRatat0ing\nzolo17\nHsmNewfriend\nJoshHillman\nDinoComparator\nDr_Bacon_Hair\n_peemcgee\nMarkstefer\nminemaster933\nbusinessmindset101 ‚Äî 3/1/2026 11:08 am\nComplexii\nzolo17\nJoshHillman\nHsmNewfriend\nDr_Bacon_Hair\nMinemaster399\ncreepilycreep\nRatat0ing\ntoasttastesprettygood ‚Äî 3/1/2026 11:12 am\nMinemaster\nHsmNewfriend\nDrbaconhair\nZolo\nCreepilyCreep\nRatatoing\nMarkstefer\nGjum ‚Äî 3/1/2026 1:54 pm\nCreepilyCreep\nRatat0ing\nComplexii\nHsmNewfriend\nZolo\nDrBaconHair\nMinemaster\npeemcgee\nCreepilyCreep ‚Äî 3/1/2026 3:45 pm\nCreepilyCreep\nRatat0ing\nComplexii\nDrBaconHair\nZolo\nminemaster \npeemcgee \nJohnHillman\nIsraelGPT ‚Äî 3/1/2026 4:59 pm\nyay ty\nDinoCompactor ‚Äî 3/1/2026 5:51 pm\nthis is the highest honor ive ever recieved....\nDinoCompactor ‚Äî 3/1/2026 6:00 pm\nit is made a little bit worse by the fact that isreal is right next to me, but then you make it up by having josh at the bottom so its all good!\nJosh ‚Äúalleged terrorist‚Äù Hillman\n\n ‚Äî 3/1/2026 7:06 pm\nthis  guy voted in THE FUCKING ORDER THAT ANVIL PUT IT IN IM DEAD BRO\nComplexii ‚Äî 3/1/2026 9:27 pm\n@Complexii \n@Mayor Ratat0ing \n@CreepilyCreep\n@CEO Zolo \n@councilor _peemcgee \n@HsmNewfriend \n@Dr Bacon Hair(real)\nJuniorTide\n\n ‚Äî 3/1/2026 9:47 pm\nDr Bacon Hair\nCEO Zolo\nCreepily\nComplexii\nJoshhillman\nRatat0ing\nPeemcgee\nMinemaster\nHsmnewfriend\nDino Comparator\nmarkstefer\nlordchieftain\n\n ‚Äî 3/1/2026 11:28 pm\n@Mayor Ratat0ing \n@CreepilyCreep \n@Complexii \n@HsmNewfriend \n@CEO Zolo \n@councilor _peemcgee \n@Dr Bacon Hair(real) \n@Josh ‚Äúalleged terrorist‚Äù Hillman \n@minemaster\n@DinoCompactor \n@IsraelGPT\nPeter Thusk\n\n ‚Äî 4/1/2026 12:29 am\nDr Baacon Hair\nMinemaster\nRato0ing\nZolo\nJoshHillman\nHsmNewfriend\n \nSpeedy J. Justice\n\n ‚Äî 4/1/2026 12:54 am\nVote this to fight venezuela speedy\n\n \nMinemaster\nHsmnewfriend\nDrBaconHair\nMarkstefer\nCreepily Creep\nRatatoing\n \nTukidoki/KiWi ‚Äî 4/1/2026 1:29 am\nMinemaster\nHsmnewfriend\nDrBaconHair\nMarkstefer\nHsmNewfriend\n\n ‚Äî 4/1/2026 1:42 am\nMinemaster\nHsmNewfriend\nDrBaconHair\nMarkstefer\nZolo17\n_peemcgee\nLucinnefo\nJoshHillman\nComplexxi\nCreepilyceep\nDinocomarator\n \nPresident Rat Twink II\n\n ‚Äî 4/1/2026 1:49 am\nComplexii\nCreepilyCreep\nRatat0ing\nzolo17\nHsmNewfriend\nJoshHillman\nDinoComparator\nDr_Bacon_Hair\n_peemcgee\nMarkstefer\nminemaster933\n'Saker\n\n ‚Äî 4/1/2026 2:08 am\nMinemaster\nHsmnewfriend\nDrBaconHair\nMarkstefer\nCreepily Creep\nRatatoing\nKronprinzKaiser ‚Äî 4/1/2026 2:57 am\nMinemaster\nHsmnewfriend\nDrBaconHair\nMarkstefer\nCreepily Creep\nRatatoing\nOkiinawa ‚Äî 4/1/2026 2:58 am\nMinemaster\nHsmnewfriend\nDrBaconHair\nMarkstefer\nCreepily Creep\nRatatoing\nGilianùïè ‚Äî 4/1/2026 3:13 am\ntoasttastesprettygood\nDrbaconhair\nComplexii\nhsmnewfriend\nZolo18\nWheatthinking\nMarkstefer\n\n67 67 67 67\nescarchaking333 ‚Äî 4/1/2026 3:25 am\nRatat0ing\nCreepilyCreep\nDrBaconHair\nZolo\nminemaster \npeemcgee \nJohnHillman\nsage ‚Äî 4/1/2026 3:25 am\n1) creep\n2) hsmnewfriend \n3) peemcgee\n4) drbaconhair \n5) joshhillman\n6) minemaster (thanks for giving me bread when i was drunk)\nPalantircios\n\n ‚Äî 4/1/2026 3:33 am\n@Mayor Ratat0ing \n@CreepilyCreep \n@Complexii \n@Dr Bacon Hair(real) \n@HsmNewfriend \n@IsraelGPT \n@DinoCompactor \n@CEO Zolo \n@toasttastesprettygood\nSpeaker ùïèergeant ClitHorris666\n\n ‚Äî 4/1/2026 3:34 am\n@toasttastesprettygood\n@Dr Bacon Hair(real)\n@HsmNewfriend \n@CEO Zolo\n@Complexii \n@Hg_67\n@Anvil \n@august \nIsraelGPT ‚Äî 4/1/2026 3:56 am\nty\naugust ‚Äî 4/1/2026 4:00 am\n@toasttastesprettygood\n@Mayor Ratat0ing\n@Complexii\n@CEO Zolo\n@councilor _peemcgee\n@CreepilyCreep\n@HsmNewfriend\n@IsraelGPT\n@Dr Bacon Hair(real)\n@Josh ‚Äúalleged terrorist‚Äù Hillman\n@DinoCompactor\naugust ‚Äî 4/1/2026 4:00 am\n@toasttastesprettygood\n@Mayor Ratat0ing\n@Complexii\n@CEO Zolo\n@councilor _peemcgee\n@CreepilyCreep\n@HsmNewfriend\n@IsraelGPT\n@Dr Bacon Hair(real)\n@Josh ‚Äúalleged terrorist‚Äù Hillman\n@DinoCompactor\nSilent\n\n ‚Äî 4/1/2026 5:13 am\n@Dr Bacon Hair(real)\n@HsmNewfriend\nMine master\n@Mayor Ratat0ing\n@councilor _peemcgee\n@CEO Zolo\n@DinoCompactor\nVedel ‚Äî 4/1/2026 5:47 am\nMinemaster\nHsmnewfriend\nDrBaconHair\nMarkstefer\nCreepily Creep\nRatatoing",
    "seats": 5
  },
  "nameMatches": {
    "HsmNewfriend": "HsmNewfriend",
    "Dr Bacon Hair": "Dr Bacon Hair",
    "CreepilyCreep": "CreepilyCreep",
    "Complexii": "Complexii",
    "Mayor Ratat0ing": "Ratat0ing",
    "CEO Zolo": "CEO Zolo",
    "toasttastesprettygood": "toasttastesprettygood",
    "Markstefer": "IsraelGPT",
    "Minemaster": "toasttastesprettygood",
    "councilor _peemcgee": "councilor _peemcgee",
    "Josh ‚Äúalleged terrorist‚Äù Hillman": "Josh ‚Äúalleged terrorist‚Äù Hillman",
    "DrBaconHair": "Dr Bacon Hair",
    "Ratat0ing": "Ratat0ing",
    "IsraelGPT": "IsraelGPT",
    "JoshHillman": "Josh ‚Äúalleged terrorist‚Äù Hillman",
    "Zolo": "CEO Zolo",
    "Ratatoing": "Ratat0ing",
    "DinoCompactor": "DinoCompactor",
    "Hsmnewfriend": "HsmNewfriend",
    "zolo17": "CEO Zolo",
    "Luci the Trident Farmer": null,
    "am": null,
    "Creepily Creep": "CreepilyCreep",
    "minemaster": "toasttastesprettygood",
    "Anvil": null,
    "DinoComparator": "DinoCompactor",
    "Dr_Bacon_Hair": "Dr Bacon Hair",
    "_peemcgee": "councilor _peemcgee",
    "Hg_67": null,
    "Lucinnefo": null,
    "minemaster933": "toasttastesprettygood",
    "Drbaconhair": "Dr Bacon Hair",
    "peemcgee": "councilor _peemcgee",
    "Lopster Bisque": null,
    "Peemcgee": "councilor _peemcgee",
    "JohnHillman": "Josh ‚Äúalleged terrorist‚Äù Hillman",
    "hg_weighty": null,
    "Baconhair": "Dr Bacon Hair",
    "Toasttastesprettygood": "toasttastesprettygood",
    "MrJeremyFisher": null,
    "specificgjumguage": null,
    "Complexiii": "Complexii",
    "Dinocomparator": "DinoCompactor",
    "Markstfu": "IsraelGPT",
    "rat": "Ratat0ing",
    "creep": "CreepilyCreep",
    "luci": null,
    "toast": "toasttastesprettygood",
    "josh": "Josh ‚Äúalleged terrorist‚Äù Hillman",
    "hsm": "HsmNewfriend",
    "complexii": "Complexii",
    ".zolo": "CEO Zolo",
    "Bacon": "Dr Bacon Hair",
    "Isreal": "IsraelGPT",
    "Minemaster399": "toasttastesprettygood",
    "creepilycreep": "CreepilyCreep",
    "Creepily": "CreepilyCreep",
    "Joshhillman": "Josh ‚Äúalleged terrorist‚Äù Hillman",
    "Dino Comparator": "DinoCompactor",
    "markstefer": "IsraelGPT",
    "Dr Baacon Hair": "Dr Bacon Hair",
    "Rato0ing": "Ratat0ing",
    "Zolo17": "CEO Zolo",
    "Complexxi": "Complexii",
    "Creepilyceep": "CreepilyCreep",
    "Dinocomarator": "DinoCompactor",
    "hsmnewfriend": "HsmNewfriend",
    "Zolo18": "CEO Zolo",
    "Wheatthinking": null,
    "67 67 67": "__NOT_A_BALLOT__",
    ") creep": "CreepilyCreep",
    ") hsmnewfriend": "HsmNewfriend",
    ") peemcgee": "councilor _peemcgee",
    ") drbaconhair": "Dr Bacon Hair",
    ") joshhillman": "Josh ‚Äúalleged terrorist‚Äù Hillman",
    ") minemaster": "toasttastesprettygood",
    "august": null,
    "ty": "__NOT_A_BALLOT__",
    "Mine master": "toasttastesprettygood"
  },
  "learnedCorrelations": {
    "minemaster": "toasttastesprettygood",
    "luci the trident farmer": null,
    "lopster bisque": null,
    "johnhillman": "Josh ‚Äúalleged terrorist‚Äù Hillman",
    "mrjeremyfisher": null,
    "specificgjumguage": null,
    "markstfu": "IsraelGPT",
    "creepilyceep": "CreepilyCreep",
    "wheatthinking": null,
    "": "__NOT_A_BALLOT__",
    "ty": "__NOT_A_BALLOT__",
    "mine master": "toasttastesprettygood"
  },
  "ballotOverrides": {},
  "originalBallotText": {
    "therecycler": "Ex-Councilor TheRecycler\n\n ‚Äî 3/1/2026 6:12 am\nRatat0ing\nDr Bacon Hair\nHsmNewfriend\nhg_weighty\nJoshHillman\nminemaster\nDinoCompactor\nzolo17 ",
    "alzubloxxer11": "AlzuBloxxer11 ‚Äî 3/1/2026 6:14 am\n@Dr Bacon Hair(real) \n@HsmNewfriend \n@Mayor Ratat0ing \n@CreepilyCreep \n@Complexii \n@Josh ‚Äúalleged terrorist‚Äù Hillman \n@toasttastesprettygood",
    "stefanmakker": "StefanMakker\n\n ‚Äî 3/1/2026 6:15 am\n@HsmNewfriend \n@Mayor Ratat0ing \n@Dr Bacon Hair(real) \n@councilor _peemcgee \n@Complexii \n@toasttastesprettygood \n@Josh ‚Äúalleged terrorist‚Äù Hillman ",
    "lopsterbisque": "Lopster Bisque ‚Äî 3/1/2026 6:15 am\n@Mayor Ratat0ing \n@CreepilyCreep \n@Complexii \n@CEO Zolo \n@IsraelGPT \n@councilor _peemcgee \n@Dr Bacon Hair(real) \n@HsmNewfriend",
    "binchymonkey": "binchymonkey\n\n ‚Äî 3/1/2026 6:16 am\n@Hg_67\n@IsraelGPT\n@Mayor Ratat0ing\n@Luci the Trident Farmer\n@Josh ‚Äúalleged terrorist‚Äù Hillman\n ",
    "drbaconhair": "Dr Bacon Hair(real)\n\n ‚Äî 3/1/2026 6:16 am\n@toasttastesprettygood \n@HsmNewfriend \n@Dr Bacon Hair(real) \n@CEO Zolo \n@Josh ‚Äúalleged terrorist‚Äù Hillman \n@Mayor Ratat0ing \n@CreepilyCreep \n@IsraelGPT \n@Luci the Trident Farmer \n@councilor _peemcgee \n@Complexii ",
    "lucithetridentfarmer": "Luci the Trident Farmer\n\n ‚Äî 3/1/2026 6:19 am\n@Luci the Trident Farmer (wasnt i banned?)\n@Josh ‚Äúalleged terrorist‚Äù Hillman \n@Dr Bacon Hair(real) \n@CreepilyCreep \n@DinoCompactor \n@councilor _peemcgee \n@Complexii \n@HsmNewfriend \n@IsraelGPT",
    "ratat0ing": "Mayor Ratat0ing\n\n ‚Äî 3/1/2026 6:20 am\n@Mayor Ratat0ing \n@CreepilyCreep \n@HsmNewfriend \n@CEO Zolo \n@Complexii \n@Dr Bacon Hair(real) \n@toasttastesprettygood ",
    "darkhelmet12e4": "Dark Helmet12E4\n\n ‚Äî 3/1/2026 6:30 am\n@Dr Bacon Hair(real)\n @CEO Zolo \n@Lopster Bisque\n @Anvil\n@HsmNewfriend ",
    "zolo": "CEO Zolo\n\n ‚Äî 3/1/2026 6:32 am\nZolo\nBaconhair\nHsmNewfriend\nComplexii\nCreepilyCreep\nRatatoing\nToasttastesprettygood (minemaster)\nMarkstefer",
    "cubine": "Cubine\n\n ‚Äî 3/1/2026 6:33 am\n@Dr Bacon Hair(real) \n@Anvil \n@CreepilyCreep \n@Luci the Trident Farmer",
    "hg_67": "Hg_67 ‚Äî 3/1/2026 6:36 am\n@MrJeremyFisher\n@specificgjumguage (write-in)\n@Hg_67 ",
    "trial_len": "trial_len (AKA Lena)\n\n ‚Äî 3/1/2026 7:03 am\n@Dr Bacon Hair(real) \n@Mayor Ratat0ing \n@toasttastesprettygood \n@Lopster Bisque \n@Anvil",
    "israelgpt": "IsraelGPT ‚Äî 3/1/2026 7:16 am\n@IsraelGPT \n@toasttastesprettygood \n@Dr Bacon Hair(real) \n@Mayor Ratat0ing \n@CreepilyCreep \n@HsmNewfriend \n@Josh ‚Äúalleged terrorist‚Äù Hillman \n@Luci the Trident Farmer \n@CEO Zolo \n@councilor _peemcgee \n@Complexii",
    "yodabird": "turbo janny yodabird ‚Äî 3/1/2026 7:16 am\nComplexii\nCreepilyCreep\nRatat0ing\nzolo17\nHsmNewfriend\nJoshHillman\nDinoComparator\nDr_Bacon_Hair\n_peemcgee\nMarkstefer\nLucinnefo\nminemaster933",
    "joshallegedterroristhillman": "Josh ‚Äúalleged terrorist‚Äù Hillman\n\n ‚Äî 3/1/2026 7:21 am\nJoshHillman\nLucinnefo (barred?)\nDr Bacon Hair\nCreepilyCreep\nRatatoing\nComplexiii\nMinemaster\nPeemcgee\nDinocomparator\nHsmNewfriend\nMarkstfu\n12.Zolo",
    "_peemcgee": "councilor _peemcgee\n\n ‚Äî 3/1/2026 8:45 am\n@councilor _peemcgee \n@Mayor Ratat0ing \n@Josh ‚Äúalleged terrorist‚Äù Hillman \n@CreepilyCreep\n@Dr Bacon Hair(real)",
    "jammymie": "jammy mie\n\n ‚Äî 3/1/2026 8:45 am\n@Dr Bacon Hair(real)\n@CreepilyCreep\n@HsmNewfriend \n@CEO Zolo\n@toasttastesprettygood ",
    "sdorr": "Sdorr\n\n ‚Äî 3/1/2026 9:09 am\n@toasttastesprettygood\n@HsmNewfriend\n3.@Dr Bacon Hair(real) \n@CEO Zolo",
    "mushroomcultist": "mushroom cultist ‚Äî 3/1/2026 10:33 am\nMinemaster\nHsmNewfriend\nDrbaconhair\nZolo ",
    "dinocompactor": "DinoCompactor ‚Äî 3/1/2026 10:48 am\n1.DinoComparator\n2.rat\n3.creep\n4.luci\n5.toast\n6.josh\n7.hsm\n8complexii\n9..zolo\n10.Bacon\n11.Isreal ",
    "gold": "Gold ‚Äî 3/1/2026 10:59 am\nComplexii\nCreepilyCreep\nRatat0ing\nzolo17\nHsmNewfriend\nJoshHillman\nDinoComparator\nDr_Bacon_Hair\n_peemcgee\nMarkstefer\nminemaster933",
    "businessmindset101": "businessmindset101 ‚Äî 3/1/2026 11:08 am\nComplexii\nzolo17\nJoshHillman\nHsmNewfriend\nDr_Bacon_Hair\nMinemaster399\ncreepilycreep\nRatat0ing",
    "toasttastesprettygood": "toasttastesprettygood ‚Äî 3/1/2026 11:12 am\nMinemaster\nHsmNewfriend\nDrbaconhair\nZolo\nCreepilyCreep\nRatatoing\nMarkstefer",
    "gjum": "Gjum ‚Äî 3/1/2026 1:54 pm\nCreepilyCreep\nRatat0ing\nComplexii\nHsmNewfriend\nZolo\nDrBaconHair\nMinemaster\npeemcgee",
    "creepilycreep": "CreepilyCreep ‚Äî 3/1/2026 3:45 pm\nCreepilyCreep\nRatat0ing\nComplexii\nDrBaconHair\nZolo\nminemaster \npeemcgee \nJohnHillman",
    "complexii": "Complexii ‚Äî 3/1/2026 9:27 pm\n@Complexii \n@Mayor Ratat0ing \n@CreepilyCreep\n@CEO Zolo \n@councilor _peemcgee \n@HsmNewfriend \n@Dr Bacon Hair(real)",
    "juniortide": "JuniorTide\n\n ‚Äî 3/1/2026 9:47 pm\nDr Bacon Hair\nCEO Zolo\nCreepily\nComplexii\nJoshhillman\nRatat0ing\nPeemcgee\nMinemaster\nHsmnewfriend\nDino Comparator\nmarkstefer",
    "lordchieftain": "lordchieftain\n\n ‚Äî 3/1/2026 11:28 pm\n@Mayor Ratat0ing \n@CreepilyCreep \n@Complexii \n@HsmNewfriend \n@CEO Zolo \n@councilor _peemcgee \n@Dr Bacon Hair(real) \n@Josh ‚Äúalleged terrorist‚Äù Hillman \n@minemaster\n@DinoCompactor \n@IsraelGPT",
    "peterthusk": "Peter Thusk\n\n ‚Äî 4/1/2026 12:29 am\nDr Baacon Hair\nMinemaster\nRato0ing\nZolo\nJoshHillman\nHsmNewfriend\n ",
    "speedyjjustice": "Speedy J. Justice\n\n ‚Äî 4/1/2026 12:54 am\nVote this to fight venezuela speedy\n\n \nMinemaster\nHsmnewfriend\nDrBaconHair\nMarkstefer\nCreepily Creep\nRatatoing\n ",
    "tukidokikiwi": "Tukidoki/KiWi ‚Äî 4/1/2026 1:29 am\nMinemaster\nHsmnewfriend\nDrBaconHair\nMarkstefer",
    "hsmnewfriend": "HsmNewfriend\n\n ‚Äî 4/1/2026 1:42 am\nMinemaster\nHsmNewfriend\nDrBaconHair\nMarkstefer\nZolo17\n_peemcgee\nLucinnefo\nJoshHillman\nComplexxi\nCreepilyceep\nDinocomarator\n ",
    "rattwinkii": "President Rat Twink II\n\n ‚Äî 4/1/2026 1:49 am\nComplexii\nCreepilyCreep\nRatat0ing\nzolo17\nHsmNewfriend\nJoshHillman\nDinoComparator\nDr_Bacon_Hair\n_peemcgee\nMarkstefer\nminemaster933",
    "saker": "'Saker\n\n ‚Äî 4/1/2026 2:08 am\nMinemaster\nHsmnewfriend\nDrBaconHair\nMarkstefer\nCreepily Creep\nRatatoing",
    "kronprinzkaiser": "KronprinzKaiser ‚Äî 4/1/2026 2:57 am\nMinemaster\nHsmnewfriend\nDrBaconHair\nMarkstefer\nCreepily Creep\nRatatoing",
    "okiinawa": "Okiinawa ‚Äî 4/1/2026 2:58 am\nMinemaster\nHsmnewfriend\nDrBaconHair\nMarkstefer\nCreepily Creep\nRatatoing",
    "gilian": "Gilianùïè ‚Äî 4/1/2026 3:13 am\ntoasttastesprettygood\nDrbaconhair\nComplexii\nhsmnewfriend\nZolo18\nWheatthinking\nMarkstefer\n\n67 67 67 67",
    "escarchaking333": "escarchaking333 ‚Äî 4/1/2026 3:25 am\nRatat0ing\nCreepilyCreep\nDrBaconHair\nZolo\nminemaster \npeemcgee \nJohnHillman",
    "sage": "sage ‚Äî 4/1/2026 3:25 am\n1) creep\n2) hsmnewfriend \n3) peemcgee\n4) drbaconhair \n5) joshhillman\n6) minemaster (thanks for giving me bread when i was drunk)",
    "palantircios": "Palantircios\n\n ‚Äî 4/1/2026 3:33 am\n@Mayor Ratat0ing \n@CreepilyCreep \n@Complexii \n@Dr Bacon Hair(real) \n@HsmNewfriend \n@IsraelGPT \n@DinoCompactor \n@CEO Zolo \n@toasttastesprettygood",
    "ergeantclithorris666": "Speaker ùïèergeant ClitHorris666\n\n ‚Äî 4/1/2026 3:34 am\n@toasttastesprettygood\n@Dr Bacon Hair(real)\n@HsmNewfriend \n@CEO Zolo\n@Complexii \n@Hg_67\n@Anvil \n@august ",
    "israelgpt#2": "IsraelGPT ‚Äî 4/1/2026 3:56 am\nty",
    "august": "august ‚Äî 4/1/2026 4:00 am\n@toasttastesprettygood\n@Mayor Ratat0ing\n@Complexii\n@CEO Zolo\n@councilor _peemcgee\n@CreepilyCreep\n@HsmNewfriend\n@IsraelGPT\n@Dr Bacon Hair(real)\n@Josh ‚Äúalleged terrorist‚Äù Hillman\n@DinoCompactor",
    "silent": "Silent\n\n ‚Äî 4/1/2026 5:13 am\n@Dr Bacon Hair(real)\n@HsmNewfriend\nMine master\n@Mayor Ratat0ing\n@councilor _peemcgee\n@CEO Zolo\n@DinoCompactor",
    "vedel": "Vedel ‚Äî 4/1/2026 5:47 am\nMinemaster\nHsmnewfriend\nDrBaconHair\nMarkstefer\nCreepily Creep\nRatatoing"
  },
  "reviewedNames": [
    "HsmNewfriend",
    "Dr Bacon Hair",
    "CreepilyCreep",
    "Complexii",
    "Mayor Ratat0ing",
    "CEO Zolo",
    "toasttastesprettygood",
    "Markstefer",
    "councilor _peemcgee",
    "Josh ‚Äúalleged terrorist‚Äù Hillman",
    "DrBaconHair",
    "Ratat0ing",
    "IsraelGPT",
    "JoshHillman",
    "Zolo",
    "Ratatoing",
    "DinoCompactor",
    "Hsmnewfriend",
    "zolo17",
    "Luci the Trident Farmer",
    "am",
    "Creepily Creep",
    "minemaster",
    "Anvil",
    "DinoComparator",
    "Dr_Bacon_Hair",
    "_peemcgee",
    "Hg_67",
    "Lucinnefo",
    "minemaster933",
    "Drbaconhair",
    "peemcgee",
    "Lopster Bisque",
    "Peemcgee",
    "JohnHillman",
    "hg_weighty",
    "Baconhair",
    "Toasttastesprettygood",
    "MrJeremyFisher",
    "specificgjumguage",
    "Complexiii",
    "Dinocomparator",
    "rat",
    "creep",
    "luci",
    "toast",
    "josh",
    "hsm",
    "complexii",
    ".zolo",
    "Bacon",
    "Isreal",
    "Minemaster399",
    "creepilycreep",
    "Creepily",
    "Joshhillman",
    "Dino Comparator",
    "markstefer",
    "Dr Baacon Hair",
    "Rato0ing",
    "Zolo17",
    "Complexxi",
    "Creepilyceep",
    "Dinocomarator",
    "hsmnewfriend",
    "Zolo18",
    "Wheatthinking",
    "67 67 67",
    ") creep",
    ") hsmnewfriend",
    ") peemcgee",
    ") drbaconhair",
    ") joshhillman",
    ") minemaster",
    "august",
    "ty",
    "Mine master"
  ],
  "uniqueNames": [
    "HsmNewfriend",
    "Dr Bacon Hair",
    "CreepilyCreep",
    "Complexii",
    "Mayor Ratat0ing",
    "CEO Zolo",
    "toasttastesprettygood",
    "Markstefer",
    "Minemaster",
    "councilor _peemcgee",
    "Josh ‚Äúalleged terrorist‚Äù Hillman",
    "DrBaconHair",
    "Ratat0ing",
    "IsraelGPT",
    "JoshHillman",
    "Zolo",
    "Ratatoing",
    "DinoCompactor",
    "Hsmnewfriend",
    "zolo17",
    "Luci the Trident Farmer",
    "am",
    "Creepily Creep",
    "minemaster",
    "Anvil",
    "DinoComparator",
    "Dr_Bacon_Hair",
    "_peemcgee",
    "Hg_67",
    "Lucinnefo",
    "minemaster933",
    "Drbaconhair",
    "peemcgee",
    "Lopster Bisque",
    "Peemcgee",
    "JohnHillman",
    "hg_weighty",
    "Baconhair",
    "Toasttastesprettygood",
    "MrJeremyFisher",
    "specificgjumguage",
    "Complexiii",
    "Dinocomparator",
    "Markstfu",
    "rat",
    "creep",
    "luci",
    "toast",
    "josh",
    "hsm",
    "complexii",
    ".zolo",
    "Bacon",
    "Isreal",
    "Minemaster399",
    "creepilycreep",
    "Creepily",
    "Joshhillman",
    "Dino Comparator",
    "markstefer",
    "Dr Baacon Hair",
    "Rato0ing",
    "Zolo17",
    "Complexxi",
    "Creepilyceep",
    "Dinocomarator",
    "hsmnewfriend",
    "Zolo18",
    "Wheatthinking",
    "67 67 67",
    ") creep",
    ") hsmnewfriend",
    ") peemcgee",
    ") drbaconhair",
    ") joshhillman",
    ") minemaster",
    "august",
    "ty",
    "Mine master"
  ],
  "nameCounts": {
    "Ratat0ing": 9,
    "Dr Bacon Hair": 23,
    "HsmNewfriend": 29,
    "hg_weighty": 1,
    "JoshHillman": 8,
    "minemaster": 4,
    "DinoCompactor": 7,
    "zolo17": 5,
    "Mayor Ratat0ing": 15,
    "CreepilyCreep": 23,
    "Complexii": 22,
    "Josh ‚Äúalleged terrorist‚Äù Hillman": 10,
    "toasttastesprettygood": 13,
    "councilor _peemcgee": 11,
    "CEO Zolo": 15,
    "IsraelGPT": 9,
    "Hg_67": 3,
    "Luci the Trident Farmer": 5,
    "Lopster Bisque": 2,
    "Anvil": 4,
    "Zolo": 8,
    "Baconhair": 1,
    "Ratatoing": 8,
    "Toasttastesprettygood": 1,
    "Markstefer": 13,
    "MrJeremyFisher": 1,
    "specificgjumguage": 1,
    "DinoComparator": 4,
    "Dr_Bacon_Hair": 4,
    "_peemcgee": 4,
    "Lucinnefo": 3,
    "minemaster933": 3,
    "Complexiii": 1,
    "Minemaster": 13,
    "Peemcgee": 2,
    "Dinocomparator": 1,
    "Markstfu": 1,
    "am": 5,
    "Drbaconhair": 3,
    "rat": 1,
    "creep": 1,
    "luci": 1,
    "toast": 1,
    "josh": 1,
    "hsm": 1,
    "complexii": 1,
    ".zolo": 1,
    "Bacon": 1,
    "Isreal": 1,
    "Minemaster399": 1,
    "creepilycreep": 1,
    "DrBaconHair": 10,
    "peemcgee": 3,
    "JohnHillman": 2,
    "Creepily": 1,
    "Joshhillman": 1,
    "Hsmnewfriend": 7,
    "Dino Comparator": 1,
    "markstefer": 1,
    "Dr Baacon Hair": 1,
    "Rato0ing": 1,
    "Creepily Creep": 5,
    "Zolo17": 1,
    "Complexxi": 1,
    "Creepilyceep": 1,
    "Dinocomarator": 1,
    "hsmnewfriend": 1,
    "Zolo18": 1,
    "Wheatthinking": 1,
    "67 67 67": 1,
    ") creep": 1,
    ") hsmnewfriend": 1,
    ") peemcgee": 1,
    ") drbaconhair": 1,
    ") joshhillman": 1,
    ") minemaster": 1,
    "august": 1,
    "ty": 1,
    "Mine master": 1
  },
  "currentState": {
    "section": "results",
    "currentNameIndex": 79,
    "currentBallotIndex": 44
  }
}